lambda_noah40povis/Student.py
lambda_noah40povis/__init__.py
lambdata_noah40povis-0.0.8.dist-info/LICENSE
lambdata_noah40povis-0.0.8.dist-info/METADATA
lambdata_noah40povis-0.0.8.dist-info/WHEEL
lambdata_noah40povis-0.0.8.dist-info/top_level.txt
lambdata_noah40povis-0.0.8.dist-info/RECORD
